optigob/__init__.py
optigob/bioenergy/__init__.py
optigob/bioenergy/bioenergy_budget.py
optigob/budget_model/__init__.py
optigob/budget_model/baseline_emissions.py
optigob/budget_model/econ_output.py
optigob/budget_model/emissions_budget.py
optigob/budget_model/landarea_budget.py
optigob/database/__init__.py
optigob/database/optigob_default_0.1.1.db
optigob/forest/__init__.py
optigob/forest/baseline_forest.py
optigob/forest/forest_budget.py
optigob/input_helper.py
optigob/livestock/__init__.py
optigob/livestock/baseline_livestock.py
optigob/livestock/livestock_budget.py
optigob/livestock/livestock_optimisation.py
optigob/logger.py
optigob/optigob.py
optigob/other_land/__init__.py
optigob/other_land/baseline_other_land.py
optigob/other_land/other_land_budget.py
optigob/protein_crops/__init__.py
optigob/protein_crops/protein_crops_budget.py
optigob/resource_manager/__init__.py
optigob/resource_manager/database_manager.py
optigob/resource_manager/import_factory.py
optigob/resource_manager/input_query.py
optigob/resource_manager/optigob_data_manager.py
optigob/static_ag/__init__.py
optigob/static_ag/baseline_static_ag.py
optigob/static_ag/static_ag_budget.py
optigob/substitution/__init__.py
optigob/substitution/substitution.py
optigob-0.1.4.dist-info/LICENSE
optigob-0.1.4.dist-info/METADATA
optigob-0.1.4.dist-info/WHEEL
optigob-0.1.4.dist-info/RECORD
