Metadata-Version: 2.3
Name: optigob
Version: 0.1.4
Summary: A land use change and environmental assessment tool based on preconfigured data animal population numbers based on negative emissions allowance
License: MIT
Author: Colm Duffy
Requires-Python: >=3.12,<4.0
Classifier: License :: OSI Approved :: MIT License
Classifier: Programming Language :: Python :: 3
Classifier: Programming Language :: Python :: 3.12
Classifier: Programming Language :: Python :: 3.13
Requires-Dist: cplex (>=22.1.2.0,<23.0.0.0)
Requires-Dist: numpy (>=2.2.4,<3.0.0)
Requires-Dist: pandas (>=2.2.3,<3.0.0)
Requires-Dist: pyomo (>=6.8.0,<7.0.0)
Requires-Dist: pyyaml (>=6.0.2,<7.0.0)
Requires-Dist: sqlalchemy (>=2.0.39,<3.0.0)
